Metadata-Version: 2.1
Name: osearch
Version: 0.1.0
Summary: Search nested lists and dicts
Home-page: https://github.com/x821938/osearch
Author: Alex Skov Jensen
Author-email: pydev@offline.dk
License: MIT
Project-URL: Documentation, https://github.com/x821938/osearch
Project-URL: Source, https://github.com/x821938/osearch
Keywords: search,list,dictionary,objects,pretty,print,json
Platform: UNKNOWN
Classifier: Programming Language :: Python :: 3
Classifier: Development Status :: 4 - Beta
Classifier: License :: OSI Approved :: MIT License
Classifier: Operating System :: OS Independent
Classifier: Topic :: Software Development :: Bug Tracking 
Classifier: Topic :: Software Development :: Testing
Classifier: Topic :: Text Processing :: Filters
Classifier: Intended Audience :: Developers
